bemol/__init__.py
bemol/datahandler/__init__.py
bemol/datahandler/common/__init__.py
bemol/datahandler/io/__init__.py
bemol/datahandler/io/sap.py
bemol/datahandler/preprocessing/__init__.py
bemol/evaluation/__init__.py
bemol/evaluation/_commons.py
bemol/evaluation/cm.py
bemol/evaluation/hist.py
bemol/evaluation/ks.py
bemol/evaluation/psi.py
bemol/evaluation/roc.py
bemol_libraries-1.1.1.dist-info/LICENSE
bemol_libraries-1.1.1.dist-info/METADATA
bemol_libraries-1.1.1.dist-info/WHEEL
bemol_libraries-1.1.1.dist-info/top_level.txt
bemol_libraries-1.1.1.dist-info/RECORD
