Metadata-Version: 2.1
Name: bemol-libraries
Version: 1.1.1
Summary: The bemol´s python package to evaluate supervised ML models, data handling, and model analysis.
Home-page: UNKNOWN
Author: Bemol IA Team
License: UNKNOWN
Platform: UNKNOWN
Classifier: Programming Language :: Python :: 3
Classifier: License :: OSI Approved :: MIT License
Classifier: Operating System :: OS Independent
Classifier: Development Status :: 4 - Beta
Requires-Python: >=3.6
License-File: LICENSE
Requires-Dist: numpy
Requires-Dist: matplotlib
Requires-Dist: pyYAML
Requires-Dist: pandas
Requires-Dist: scipy
Requires-Dist: nb-black
Requires-Dist: pytest
Requires-Dist: scikit-learn
Requires-Dist: scikit-plot
Requires-Dist: tdqm
Requires-Dist: seaborn
